biospectools/__init__.py
biospectools/py.typed
biospectools/models/__init__.py
biospectools/models/_pls.py
biospectools/models/sparse_pls.py
biospectools/preprocessing/__init__.py
biospectools/preprocessing/criterions.py
biospectools/preprocessing/dsae.py
biospectools/preprocessing/emsc.py
biospectools/preprocessing/fringe_emsc.py
biospectools/preprocessing/me_emsc.py
biospectools/private/__init__.py
biospectools/utils/__init__.py
biospectools/utils/deprecated.py
biospectools/utils/downloads.py
biospectools/utils/interpolate.py
biospectools-0.4.0.dist-info/METADATA
biospectools-0.4.0.dist-info/WHEEL
biospectools-0.4.0.dist-info/top_level.txt
biospectools-0.4.0.dist-info/RECORD
