Metadata-Version: 2.1
Name: biospectools
Version: 0.4.0
Summary: Python tools for processing spectral data
Home-page: https://github.com/BioSpecNorway/biospectools
Author: BioSpecNorway Group
Project-URL: BiospecNorway Group, https://www.nmbu.no/en/faculty/realtek/research/groups/biospectroscopy
Requires-Python: >=3.6
Requires-Dist: numpy
Requires-Dist: scipy
Requires-Dist: scikit-learn
Requires-Dist: numexpr
Requires-Dist: tqdm
Requires-Dist: packaging
Provides-Extra: dl
Requires-Dist: tensorflow (>=2.3.4) ; extra == 'dl'
Provides-Extra: docs
Requires-Dist: sphinx (>=4.3.0) ; extra == 'docs'
Requires-Dist: myst-parser (>=0.16.0) ; extra == 'docs'
Requires-Dist: sphinx-rtd-theme ; extra == 'docs'
Provides-Extra: testing
Requires-Dist: pytest (>=6.0) ; extra == 'testing'
Requires-Dist: pytest-cov (>=2.0) ; extra == 'testing'
Requires-Dist: pandas ; extra == 'testing'
Requires-Dist: openpyxl ; extra == 'testing'
Requires-Dist: xlrd ; extra == 'testing'
Requires-Dist: flake8 (>=3.9) ; extra == 'testing'
Requires-Dist: tox (>=3.24) ; extra == 'testing'
